{
  "annotations": {
    "list": [
      {
        "builtIn": 1,
        "datasource": { "type": "datasource", "uid": "grafana" },
        "enable": true,
        "hide": true,
        "iconColor": "rgba(0, 211, 255, 1)",
        "name": "Annotations & Alerts",
        "target": { "limit": 100, "matchAny": false, "tags": [], "type": "dashboard" },
        "type": "dashboard"
      }
    ]
  },
  "editable": true,
  "fiscalYearStartMonth": 0,
  "graphTooltip": 1,
  "panels": [
    {
      "datasource": "VictoriaMetrics",
      "description": "Whether the comin service is running and reachable",
      "fieldConfig": {
        "defaults": {
          "color": { "mode": "thresholds" },
          "mappings": [
            { "options": { "0": { "color": "red", "index": 0, "text": "Down" } }, "type": "value" },
            { "options": { "1": { "color": "green", "index": 1, "text": "Up" } }, "type": "value" }
          ],
          "thresholds": {
            "mode": "absolute",
            "steps": [
              { "color": "red", "value": null },
              { "color": "green", "value": 1 }
            ]
          }
        },
        "overrides": []
      },
      "gridPos": { "h": 4, "w": 8, "x": 0, "y": 0 },
      "id": 1,
      "options": {
        "colorMode": "background",
        "graphMode": "none",
        "justifyMode": "auto",
        "orientation": "auto",
        "reduceOptions": { "calcs": ["lastNotNull"], "fields": "", "values": false },
        "textMode": "auto"
      },
      "targets": [
        {
          "expr": "up{job=\"comin\"}",
          "legendFormat": "{{instance}}",
          "refId": "A"
        }
      ],
      "title": "Service",
      "type": "stat"
    },
    {
      "datasource": "VictoriaMetrics",
      "description": "Machines that need a reboot after a deployment",
      "fieldConfig": {
        "defaults": {
          "color": { "mode": "thresholds" },
          "mappings": [
            { "options": { "0": { "color": "green", "index": 0, "text": "No" } }, "type": "value" },
            { "options": { "1": { "color": "orange", "index": 1, "text": "Yes" } }, "type": "value" }
          ],
          "thresholds": {
            "mode": "absolute",
            "steps": [
              { "color": "green", "value": null },
              { "color": "orange", "value": 1 }
            ]
          }
        },
        "overrides": []
      },
      "gridPos": { "h": 4, "w": 8, "x": 8, "y": 0 },
      "id": 2,
      "options": {
        "colorMode": "background",
        "graphMode": "none",
        "justifyMode": "auto",
        "orientation": "auto",
        "reduceOptions": { "calcs": ["lastNotNull"], "fields": "", "values": false },
        "textMode": "auto"
      },
      "targets": [
        {
          "expr": "comin_need_to_reboot",
          "legendFormat": "{{instance}}",
          "refId": "A"
        }
      ],
      "title": "Needs Reboot",
      "type": "stat"
    },
    {
      "datasource": "VictoriaMetrics",
      "description": "Machines where comin is suspended (not polling)",
      "fieldConfig": {
        "defaults": {
          "color": { "mode": "thresholds" },
          "mappings": [
            { "options": { "0": { "color": "green", "index": 0, "text": "Active" } }, "type": "value" },
            { "options": { "1": { "color": "yellow", "index": 1, "text": "Suspended" } }, "type": "value" }
          ],
          "thresholds": {
            "mode": "absolute",
            "steps": [
              { "color": "green", "value": null },
              { "color": "yellow", "value": 1 }
            ]
          }
        },
        "overrides": []
      },
      "gridPos": { "h": 4, "w": 8, "x": 16, "y": 0 },
      "id": 3,
      "options": {
        "colorMode": "background",
        "graphMode": "none",
        "justifyMode": "auto",
        "orientation": "auto",
        "reduceOptions": { "calcs": ["lastNotNull"], "fields": "", "values": false },
        "textMode": "auto"
      },
      "targets": [
        {
          "expr": "comin_is_suspended",
          "legendFormat": "{{instance}}",
          "refId": "A"
        }
      ],
      "title": "Suspended",
      "type": "stat"
    },
    {
      "datasource": "VictoriaMetrics",
      "description": "Deployed commit and status per machine (appears after first deployment)",
      "fieldConfig": {
        "defaults": {
          "color": { "mode": "fixed", "fixedColor": "text" },
          "custom": { "filterable": false },
          "thresholds": {
            "mode": "absolute",
            "steps": [{ "color": "green", "value": null }]
          }
        },
        "overrides": []
      },
      "gridPos": { "h": 10, "w": 24, "x": 0, "y": 4 },
      "id": 4,
      "options": {
        "showHeader": true,
        "sortBy": [{ "desc": false, "displayName": "instance" }]
      },
      "targets": [
        {
          "expr": "comin_deployment_info",
          "format": "table",
          "instant": true,
          "legendFormat": "",
          "refId": "A"
        }
      ],
      "transformations": [
        {
          "id": "filterFieldsByName",
          "options": {
            "include": {
              "names": ["instance", "commit_id", "status"]
            }
          }
        }
      ],
      "title": "Last Deployment",
      "type": "table"
    },
    {
      "datasource": "VictoriaMetrics",
      "description": "Service uptime over time",
      "fieldConfig": {
        "defaults": {
          "color": { "mode": "palette-classic" },
          "custom": {
            "drawStyle": "line",
            "fillOpacity": 10,
            "lineWidth": 2,
            "pointSize": 5,
            "showPoints": "never",
            "stacking": { "group": "A", "mode": "none" }
          },
          "mappings": [
            { "options": { "0": { "color": "red", "index": 0, "text": "Down" } }, "type": "value" },
            { "options": { "1": { "color": "green", "index": 1, "text": "Up" } }, "type": "value" }
          ],
          "max": 1,
          "min": 0,
          "thresholds": {
            "mode": "absolute",
            "steps": [
              { "color": "red", "value": null },
              { "color": "green", "value": 1 }
            ]
          }
        },
        "overrides": []
      },
      "gridPos": { "h": 6, "w": 24, "x": 0, "y": 14 },
      "id": 5,
      "options": {
        "legend": { "calcs": [], "displayMode": "list", "placement": "bottom" },
        "tooltip": { "mode": "multi", "sort": "desc" }
      },
      "targets": [
        {
          "expr": "up{job=\"comin\"}",
          "legendFormat": "{{instance}}",
          "refId": "A"
        }
      ],
      "title": "Service Uptime",
      "type": "timeseries"
    }
  ],
  "schemaVersion": 38,
  "style": "dark",
  "tags": ["comin", "gitops"],
  "templating": { "list": [] },
  "time": { "from": "now-24h", "to": "now" },
  "timepicker": {},
  "timezone": "",
  "title": "comin - GitOps Deployments",
  "uid": "comin-gitops",
  "version": 3
}
